{
  "parent": "minecraft:recipes/root",
  "criteria": {
    "has_spruce_logs": {
      "conditions": {
        "items": [
          {
            "items": "#minecraft:spruce_stripped_wood"
          }
        ]
      },
      "trigger": "minecraft:inventory_changed"
    },
    "has_the_recipe": {
      "conditions": {
        "recipe": "minecraft:stripped_spruce_wood_slab"
      },
      "trigger": "minecraft:recipe_unlocked"
    }
  },
  "requirements": [
    [
      "has_the_recipe",
      "has_spruce_logs"
    ]
  ],
  "rewards": {
    "recipes": [
      "minecraft:stripped_spruce_wood_slab"
    ]
  }
}